cGNF/__init__.py
cGNF/bootstraping.py
cGNF/processing.py
cGNF/processing_parallel.py
cGNF/simulation.py
cGNF/simulation_parallel.py
cGNF/training.py
cGNF/training_parallel.py
cGNF/GNF_Modules/MLP.py
cGNF/GNF_Modules/NormalizingFlow.py
cGNF/GNF_Modules/NormalizingFlowFactories.py
cGNF/GNF_Modules/__init__.py
cGNF/GNF_Modules/Conditionners/AutoregressiveConditioner.py
cGNF/GNF_Modules/Conditionners/Conditioner.py
cGNF/GNF_Modules/Conditionners/CouplingConditioner.py
cGNF/GNF_Modules/Conditionners/DAGConditioner.py
cGNF/GNF_Modules/Conditionners/__init__.py
cGNF/GNF_Modules/Normalizers/AffineNormalizer.py
cGNF/GNF_Modules/Normalizers/MonotonicNormalizer.py
cGNF/GNF_Modules/Normalizers/Normalizer.py
cGNF/GNF_Modules/Normalizers/__init__.py
cGNF-1.0.0.dist-info/LICENSE
cGNF-1.0.0.dist-info/METADATA
cGNF-1.0.0.dist-info/WHEEL
cGNF-1.0.0.dist-info/top_level.txt
cGNF-1.0.0.dist-info/RECORD
