Metadata-Version: 2.1
Name: cGNF
Version: 1.0.0
Summary: A Python Module for Implementing causal-Graphical Normalizing Flows.
Home-page: https://github.com/cGNF-Dev/cGNF
Author: cGNF-Team
Author-email: cgnf.team@gmail.com
License: BSD License
Platform: UNKNOWN
Classifier: Programming Language :: Python :: 3
Classifier: Programming Language :: Python :: 3.9
Classifier: License :: OSI Approved :: BSD License
Classifier: Operating System :: OS Independent
Requires-Dist: torch
Requires-Dist: numpy
Requires-Dist: pandas
Requires-Dist: networkx
Requires-Dist: scikit-learn
Requires-Dist: causalgraphicalmodels
Requires-Dist: UMNN
Requires-Dist: joblib
